{
    "sourceFile": "backend/routes/ingredient_categories_route.js",
    "activeCommit": 0,
    "commits": [
        {
            "activePatchIndex": 3,
            "patches": [
                {
                    "date": 1740743280634,
                    "content": "Index: \n===================================================================\n--- \n+++ \n"
                },
                {
                    "date": 1740743328096,
                    "content": "Index: \n===================================================================\n--- \n+++ \n@@ -2,4 +2,14 @@\n const router = express.Router();\r\n \r\n const dataDB = require('../models/ingredients_categories');\r\n \r\n+router.get('/', async (req, res) => {\r\n+    try {\r\n+        const result = await dataDB.find();\r\n+        res.json(result);\r\n+    } catch (error) {\r\n+        res.status(500).json({ message: error.message });\r\n+    }\r\n+});\r\n+\r\n+module.exports = router;\n\\ No newline at end of file\n"
                },
                {
                    "date": 1740743779787,
                    "content": "Index: \n===================================================================\n--- \n+++ \n@@ -1,9 +1,9 @@\n const express = require('express');\r\n const router = express.Router();\r\n+const dataDB = require('../models/ingredients_categories'); // เรียกใช้ Model\r\n \r\n-const dataDB = require('../models/ingredients_categories');\r\n-\r\n+// Route ดึงข้อมูลทั้งหมด\r\n router.get('/', async (req, res) => {\r\n     try {\r\n         const result = await dataDB.find();\r\n         res.json(result);\r\n@@ -11,5 +11,5 @@\n         res.status(500).json({ message: error.message });\r\n     }\r\n });\r\n \r\n-module.exports = router;\n\\ No newline at end of file\n+module.exports = router; // ต้องมีบรรทัดนี้เพื่อให้ `require()` ใช้งานได้\r\n"
                },
                {
                    "date": 1740743795992,
                    "content": "Index: \n===================================================================\n--- \n+++ \n@@ -1,9 +1,8 @@\n const express = require('express');\r\n const router = express.Router();\r\n-const dataDB = require('../models/ingredients_categories'); // เรียกใช้ Model\r\n+const dataDB = require('../models/ingredients_categories');\r\n \r\n-// Route ดึงข้อมูลทั้งหมด\r\n router.get('/', async (req, res) => {\r\n     try {\r\n         const result = await dataDB.find();\r\n         res.json(result);\r\n@@ -11,5 +10,5 @@\n         res.status(500).json({ message: error.message });\r\n     }\r\n });\r\n \r\n-module.exports = router; // ต้องมีบรรทัดนี้เพื่อให้ `require()` ใช้งานได้\r\n+module.exports = router;\r\n"
                }
            ],
            "date": 1740743280634,
            "name": "Commit-0",
            "content": "const express = require('express');\r\nconst router = express.Router();\r\n\r\nconst dataDB = require('../models/ingredients_categories');\r\n\r\n"
        }
    ]
}